ezpydub/__init__.py
ezpydub/ezpydub.py
ezpydub-0.2.0.dist-info/licenses/LICENSE
ezpydub-0.2.0.dist-info/METADATA
ezpydub-0.2.0.dist-info/WHEEL
ezpydub-0.2.0.dist-info/top_level.txt
ezpydub-0.2.0.dist-info/RECORD
