Metadata-Version: 2.4
Name: ezpydub
Version: 0.2.0
Summary: A simplified interface for pydub audio manipulation
Home-page: https://github.com/ TheNeodev/ezpydub
Author: TheNeodev
Author-email: TheNeoDev <neoforevershog@gmail.com>
License: This is free and unencumbered software released into the public domain.
Project-URL: Homepage, https://github.com/TheNeodev/ezpydub
Project-URL: Repository, https://github.com/TheNeodev/ezpydub
Classifier: Programming Language :: Python :: 3
Classifier: Programming Language :: Python :: 3.11
Classifier: License :: OSI Approved :: MIT License
Classifier: Operating System :: OS Independent
Requires-Python: >=3.9
License-File: LICENSE
Requires-Dist: pydub>=0.25.1
Requires-Dist: ffmpeg-python>=0.2.0
Dynamic: license-file
